squeezeformer/__init__.py
squeezeformer/activation.py
squeezeformer/attention.py
squeezeformer/convolution.py
squeezeformer/encoder.py
squeezeformer/model.py
squeezeformer/modules.py
squeezeformer-1.0.0.dist-info/LICENSE
squeezeformer-1.0.0.dist-info/METADATA
squeezeformer-1.0.0.dist-info/WHEEL
squeezeformer-1.0.0.dist-info/top_level.txt
squeezeformer-1.0.0.dist-info/RECORD
