Metadata-Version: 2.1
Name: squeezeformer
Version: 1.0.0
Summary: An Efficient Transformer for Automatic Speech Recognition
Home-page: https://github.com/upskyy/Squeezeformer
Author: Ha Sangchun
Author-email: seomk9896@gmail.com
License: UNKNOWN
Keywords: asr,speech_recognition,artificial intelligence
Platform: UNKNOWN
Requires-Python: >=3.6
License-File: LICENSE
Requires-Dist: torch (>=1.4.0)
Requires-Dist: numpy
